[
  {
    "text": "Hello, this is Kokoro running on Apple's CoreML.",
    "phonemes": "h…ôlňąO, √į…™s …™z k…ôkňą…Ē…ĻO …Ļňą Ćn…™Ňč ňĆ…Ēn ňą√¶pŠĶälz kňĆ…Ē…ĻňĆ…õmňą…õl.",
    "input_ids": [
      0,
      50,
      83,
      54,
      156,
      31,
      3,
      16,
      81,
      102,
      61,
      16,
      102,
      68,
      16,
      53,
      83,
      53,
      156,
      76,
      123,
      31,
      16,
      123,
      156,
      138,
      56,
      102,
      112,
      16,
      157,
      76,
      56,
      16,
      156,
      72,
      58,
      42,
      54,
      68,
      16,
      53,
      157,
      76,
      123,
      157,
      86,
      55,
      156,
      86,
      54,
      4,
      0
    ],
    "language": "en"
  },
  {
    "text": "The quick brown fox jumps over the lazy dog.",
    "phonemes": "√į…ô kwňą…™k b…ĻňąWn fňą…Ďks  §ňą Ćmps ňąOv…ô…Ļ √į…ô lňąAzi dňą…Ē…°.",
    "input_ids": [
      0,
      81,
      83,
      16,
      53,
      65,
      156,
      102,
      53,
      16,
      44,
      123,
      156,
      39,
      56,
      16,
      48,
      156,
      69,
      53,
      61,
      16,
      82,
      156,
      138,
      55,
      58,
      61,
      16,
      156,
      31,
      64,
      83,
      123,
      16,
      81,
      83,
      16,
      54,
      156,
      24,
      68,
      51,
      16,
      46,
      156,
      76,
      92,
      4,
      0
    ],
    "language": "en"
  },
  {
    "text": "I have a dream that one day this nation will rise up.",
    "phonemes": "ňĆI h√¶v …ź d…Ļňąim √įňą√¶t wňą Ćn dňąA √į…™s nňąA É…ôn w…™l …ĻňąIz ňĆ Ćp.",
    "input_ids": [
      0,
      157,
      25,
      16,
      50,
      72,
      64,
      16,
      70,
      16,
      46,
      123,
      156,
      51,
      55,
      16,
      81,
      156,
      72,
      62,
      16,
      65,
      156,
      138,
      56,
      16,
      46,
      156,
      24,
      16,
      81,
      102,
      61,
      16,
      56,
      156,
      24,
      131,
      83,
      56,
      16,
      65,
      102,
      54,
      16,
      123,
      156,
      25,
      68,
      16,
      157,
      138,
      58,
      4,
      0
    ],
    "language": "en"
  },
  {
    "text": "To be, or not to be, that is the question.",
    "phonemes": "t…ô bňąi, …Ē…Ļ nňĆ…Ďt t…ô bňąi, √įňą√¶t …™z √į…ô kwňą…õs ßŠĶän.",
    "input_ids": [
      0,
      62,
      83,
      16,
      44,
      156,
      51,
      3,
      16,
      76,
      123,
      16,
      56,
      157,
      69,
      62,
      16,
      62,
      83,
      16,
      44,
      156,
      51,
      3,
      16,
      81,
      156,
      72,
      62,
      16,
      102,
      68,
      16,
      81,
      83,
      16,
      53,
      65,
      156,
      86,
      61,
      133,
      42,
      56,
      4,
      0
    ],
    "language": "en"
  },
  {
    "text": "How can I help you today?",
    "phonemes": "hňĆW k√¶n ňĆI hňą…õlp ju t…ôdňąA?",
    "input_ids": [
      0,
      50,
      157,
      39,
      16,
      53,
      72,
      56,
      16,
      157,
      25,
      16,
      50,
      156,
      86,
      54,
      58,
      16,
      52,
      63,
      16,
      62,
      83,
      46,
      156,
      24,
      6,
      0
    ],
    "language": "en"
  },
  {
    "text": "Welcome to the future of on-device speech synthesis.",
    "phonemes": "wňą…õlk…ôm t…ô √į…ô fjňąu ß…ô…Ļ  Ćv ňĆ…Ēnd…ôvňąIs spňąi ß sňą…™nőł…ôs…™s.",
    "input_ids": [
      0,
      65,
      156,
      86,
      54,
      53,
      83,
      55,
      16,
      62,
      83,
      16,
      81,
      83,
      16,
      48,
      52,
      156,
      63,
      133,
      83,
      123,
      16,
      138,
      64,
      16,
      157,
      76,
      56,
      46,
      83,
      64,
      156,
      25,
      61,
      16,
      61,
      58,
      156,
      51,
      133,
      16,
      61,
      156,
      102,
      56,
      119,
      83,
      61,
      102,
      61,
      4,
      0
    ],
    "language": "en"
  },
  {
    "text": "It was the best of times, it was the worst of times.",
    "phonemes": "ňĆ…™t w Ćz √į…ô bňą…õst  Ćv tňąImz, …™t w Ćz √į…ô wňą…ú…Ļst  Ćv tňąImz.",
    "input_ids": [
      0,
      157,
      102,
      62,
      16,
      65,
      138,
      68,
      16,
      81,
      83,
      16,
      44,
      156,
      86,
      61,
      62,
      16,
      138,
      64,
      16,
      62,
      156,
      25,
      55,
      68,
      3,
      16,
      102,
      62,
      16,
      65,
      138,
      68,
      16,
      81,
      83,
      16,
      65,
      156,
      87,
      123,
      61,
      62,
      16,
      138,
      64,
      16,
      62,
      156,
      25,
      55,
      68,
      4,
      0
    ],
    "language": "en"
  },
  {
    "text": "We choose to go to the moon in this decade.",
    "phonemes": "wňĆi  ßňąuz t…ô …°ňĆO t…ô √į…ô mňąun …™n √į…™s dňą…õkňĆAd.",
    "input_ids": [
      0,
      65,
      157,
      51,
      16,
      133,
      156,
      63,
      68,
      16,
      62,
      83,
      16,
      92,
      157,
      31,
      16,
      62,
      83,
      16,
      81,
      83,
      16,
      55,
      156,
      63,
      56,
      16,
      102,
      56,
      16,
      81,
      102,
      61,
      16,
      46,
      156,
      86,
      53,
      157,
      24,
      46,
      4,
      0
    ],
    "language": "en"
  },
  {
    "text": "„Āď„āď„Āę„Ā°„ĀĮ„ÄĀ„Āď„āĆ„ĀĮ„ā≥„āĘ„ā®„É†„ā®„Éę„Āģ„ÉÜ„āĻ„Éą„Āß„Āô„Äā",
    "phonemes": "ko…≤…≤i ®iő≤a ko…ĺe ő≤a koaem…Įe…ĺ…Į no tes…®to des…®",
    "input_ids": [
      0,
      53,
      57,
      114,
      114,
      51,
      21,
      51,
      75,
      43,
      16,
      53,
      57,
      125,
      47,
      16,
      75,
      43,
      16,
      53,
      57,
      43,
      47,
      55,
      110,
      47,
      125,
      110,
      16,
      56,
      57,
      16,
      62,
      47,
      61,
      101,
      62,
      57,
      16,
      46,
      47,
      61,
      101,
      0
    ],
    "language": "ja"
  },
  {
    "text": "šĽäśó•„ĀĮ„Ā®„Ā¶„āāŤČĮ„ĀĄŚ§©śįó„Āß„Āô„Ā≠„Äā",
    "phonemes": "k ≤oňź ő≤a totemo joi teŇčk ≤i des…® ne",
    "input_ids": [
      0,
      53,
      164,
      57,
      158,
      16,
      75,
      43,
      16,
      62,
      57,
      62,
      47,
      55,
      57,
      16,
      52,
      57,
      51,
      16,
      62,
      47,
      112,
      53,
      164,
      51,
      16,
      46,
      47,
      61,
      101,
      16,
      56,
      47,
      0
    ],
    "language": "ja"
  },
  {
    "text": "ÁßĀ„ĀĮśĚĪšļ¨„ĀęšĹŹ„āď„Āß„ĀĄ„Āĺ„Āô„Äā",
    "phonemes": "ő≤atak…Į…ēi ő≤a toňźk ≤oňź …≤i s…®nde imas…®",
    "input_ids": [
      0,
      75,
      43,
      62,
      43,
      53,
      110,
      77,
      51,
      16,
      75,
      43,
      16,
      62,
      57,
      158,
      53,
      164,
      57,
      158,
      16,
      114,
      51,
      16,
      61,
      101,
      56,
      46,
      47,
      16,
      51,
      55,
      43,
      61,
      101,
      0
    ],
    "language": "ja"
  },
  {
    "text": "šļļŚ∑•Áü•ŤÉĹ„ĀĮśú™śĚ•„āíŚ§Č„Āą„āč„Āß„Āó„āá„ĀÜ„Äā",
    "phonemes": " •iŇčkoňź  ®inoňź ő≤a m ≤i…ĺai o kae…ĺ…Į de…ēoňź",
    "input_ids": [
      0,
      19,
      51,
      112,
      53,
      57,
      158,
      16,
      21,
      51,
      56,
      57,
      158,
      16,
      75,
      43,
      16,
      55,
      164,
      51,
      125,
      43,
      51,
      16,
      57,
      16,
      53,
      43,
      47,
      125,
      110,
      16,
      46,
      47,
      77,
      57,
      158,
      0
    ],
    "language": "ja"
  },
  {
    "text": "„ā≥„Éľ„Éí„Éľ„āíšłÄśĚĮ„ĀŹ„Ā†„Āē„ĀĄ„Äā",
    "phonemes": "koňź√ßiňź o i Ēpai k…Įdasai",
    "input_ids": [
      0,
      53,
      57,
      158,
      78,
      51,
      158,
      16,
      57,
      16,
      51,
      148,
      58,
      43,
      51,
      16,
      53,
      110,
      46,
      43,
      61,
      43,
      51,
      0
    ],
    "language": "ja"
  }
]